aws_logger/__init__.py
aws_logger/awslogger.py
aceawslogger-0.2.1.dist-info/METADATA
aceawslogger-0.2.1.dist-info/WHEEL
aceawslogger-0.2.1.dist-info/top_level.txt
aceawslogger-0.2.1.dist-info/RECORD
