Metadata-Version: 2.1
Name: aceawslogger
Version: 0.2.1
Summary: AWS Logger
Author: ace
Author-email: kardaras.george@clublabs.com
